dreamsim/__init__.py
dreamsim/config.py
dreamsim/constants.py
dreamsim/model.py
dreamsim/feature_extraction/__init__.py
dreamsim/feature_extraction/extractor.py
dreamsim/feature_extraction/load_clip_as_dino.py
dreamsim/feature_extraction/load_mae_as_vit.py
dreamsim/feature_extraction/load_open_clip_as_dino.py
dreamsim/feature_extraction/vision_transformer.py
dreamsim-0.2.0.dist-info/LICENSE
dreamsim-0.2.0.dist-info/METADATA
dreamsim-0.2.0.dist-info/WHEEL
dreamsim-0.2.0.dist-info/top_level.txt
dreamsim-0.2.0.dist-info/RECORD
