Metadata-Version: 2.1
Name: dreamsim
Version: 0.2.0
Summary: DreamSim similarity metric
Home-page: https://github.com/ssundaram21/dreamsim
Classifier: Programming Language :: Python :: 3
Classifier: License :: OSI Approved :: MIT License
Classifier: Operating System :: OS Independent
License-File: LICENSE
Requires-Dist: numpy
Requires-Dist: open-clip-torch
Requires-Dist: peft
Requires-Dist: Pillow
Requires-Dist: torch
Requires-Dist: timm
Requires-Dist: scipy
Requires-Dist: torchvision
Requires-Dist: transformers
